pysoa/__init__.py
pysoa/py.typed
pysoa/typing_patches.py
pysoa/utils.py
pysoa/version.py
pysoa/client/__init__.py
pysoa/client/client.py
pysoa/client/errors.py
pysoa/client/expander.py
pysoa/client/middleware.py
pysoa/client/settings.py
pysoa/common/__init__.py
pysoa/common/compatibility.py
pysoa/common/constants.py
pysoa/common/errors.py
pysoa/common/logging.py
pysoa/common/settings.py
pysoa/common/types.py
pysoa/common/serializer/__init__.py
pysoa/common/serializer/base.py
pysoa/common/serializer/errors.py
pysoa/common/serializer/json_serializer.py
pysoa/common/serializer/msgpack_serializer.py
pysoa/common/transport/__init__.py
pysoa/common/transport/base.py
pysoa/common/transport/errors.py
pysoa/common/transport/local.py
pysoa/common/transport/redis_gateway/__init__.py
pysoa/common/transport/redis_gateway/client.py
pysoa/common/transport/redis_gateway/constants.py
pysoa/common/transport/redis_gateway/core.py
pysoa/common/transport/redis_gateway/server.py
pysoa/common/transport/redis_gateway/settings.py
pysoa/common/transport/redis_gateway/utils.py
pysoa/common/transport/redis_gateway/backend/__init__.py
pysoa/common/transport/redis_gateway/backend/base.py
pysoa/common/transport/redis_gateway/backend/sentinel.py
pysoa/common/transport/redis_gateway/backend/standard.py
pysoa/server/__init__.py
pysoa/server/autoreload.py
pysoa/server/coroutine.py
pysoa/server/errors.py
pysoa/server/middleware.py
pysoa/server/schemas.py
pysoa/server/server.py
pysoa/server/settings.py
pysoa/server/standalone.py
pysoa/server/types.py
pysoa/server/action/__init__.py
pysoa/server/action/base.py
pysoa/server/action/introspection.py
pysoa/server/action/status.py
pysoa/server/action/switched.py
pysoa/server/django/__init__.py
pysoa/server/django/cache.py
pysoa/server/django/database.py
pysoa/server/internal/__init__.py
pysoa/server/internal/event_loop.py
pysoa/server/internal/types.py
pysoa/test/__init__.py
pysoa/test/assertions.py
pysoa/test/compatibility.py
pysoa/test/factories.py
pysoa-1.4.9.dist-info/LICENSE
pysoa-1.4.9.dist-info/METADATA
pysoa-1.4.9.dist-info/WHEEL
pysoa-1.4.9.dist-info/entry_points.txt
pysoa-1.4.9.dist-info/top_level.txt
pysoa-1.4.9.dist-info/RECORD
