Metadata-Version: 2.1
Name: pysoa
Version: 1.4.9
Summary: A Python library for writing (micro)services and their clients
Home-page: http://github.com/eventbrite/pysoa
Author: Eventbrite, Inc.
Author-email: opensource@eventbrite.com
License: Apache 2.0
Project-URL: Documentation, https://pysoa.readthedocs.io
Project-URL: Issues, https://github.com/eventbrite/pysoa/issues
Project-URL: CI, https://travis-ci.org/eventbrite/pysoa/
Classifier: Development Status :: 5 - Production/Stable
Classifier: Intended Audience :: Developers
Classifier: License :: OSI Approved :: Apache Software License
Classifier: Operating System :: OS Independent
Classifier: Programming Language :: Python
Classifier: Programming Language :: Python :: 2
Classifier: Programming Language :: Python :: 2.7
Classifier: Programming Language :: Python :: 3
Classifier: Programming Language :: Python :: 3.5
Classifier: Programming Language :: Python :: 3.6
Classifier: Programming Language :: Python :: 3.7
Classifier: Programming Language :: Python :: 3.8
Classifier: Topic :: Software Development
License-File: LICENSE
Requires-Dist: attrs (<22,>=18.2)
Requires-Dist: conformity (~=1.28)
Requires-Dist: currint (<3,>=1.6)
Requires-Dist: msgpack (>=0.6.2,~=0.6)
Requires-Dist: pymetrics (~=1.0.7)
Requires-Dist: pytz (>=2019.1)
Requires-Dist: redis (!=3.0.*,!=3.1.*,!=3.2.*,!=3.3.*,<4.0,>=2.10)
Requires-Dist: six (~=1.10)
Requires-Dist: enum34 ; python_version < "3.4"
Requires-Dist: typing (~=3.7.4) ; python_version < "3.5"
Requires-Dist: contextvars (==2.4) ; python_version > "3.4" and python_version < "3.7"
Requires-Dist: aiocontextvars (==0.2.2) ; python_version > "3.4" and python_version < "3.7"
Provides-Extra: docs
Requires-Dist: conformity[docs] (>=1.26.4,~=1.26) ; extra == 'docs'
Requires-Dist: django (~=1.11) ; extra == 'docs'
Requires-Dist: pyparsing (~=2.2) ; extra == 'docs'
Requires-Dist: pytest (<5.4,>4.2) ; extra == 'docs'
Requires-Dist: mock (>=2.0) ; (python_version < "3.3") and extra == 'docs'
Requires-Dist: pytest-asyncio (~=0.10.0) ; (python_version > "3.4") and extra == 'docs'
Requires-Dist: Faker (~=5.0.0) ; (python_version > "3.4") and extra == 'docs'
Requires-Dist: sphinx (~=2.2) ; (python_version >= "3.6") and extra == 'docs'
Provides-Extra: test_helpers
Requires-Dist: mock (>=2.0) ; (python_version < "3.3") and extra == 'test_helpers'
Provides-Extra: test_plans
Requires-Dist: pyparsing (~=2.2) ; extra == 'test_plans'
Requires-Dist: pytest (<5.4,>4.2) ; extra == 'test_plans'
Requires-Dist: mock (>=2.0) ; (python_version < "3.3") and extra == 'test_plans'
Requires-Dist: pytest-asyncio (~=0.10.0) ; (python_version > "3.4") and extra == 'test_plans'
Requires-Dist: Faker (~=5.0.0) ; (python_version > "3.4") and extra == 'test_plans'
Provides-Extra: testing
Requires-Dist: coverage (~=4.5) ; extra == 'testing'
Requires-Dist: factory-boy (~=2.11.1) ; extra == 'testing'
Requires-Dist: freezegun (~=0.3) ; extra == 'testing'
Requires-Dist: lunatic-python-universal (~=2.1) ; extra == 'testing'
Requires-Dist: mockredispy (~=2.9) ; extra == 'testing'
Requires-Dist: parameterized (~=0.7) ; extra == 'testing'
Requires-Dist: pyparsing (~=2.2) ; extra == 'testing'
Requires-Dist: pytest (<5.4,>4.2) ; extra == 'testing'
Requires-Dist: mock (>=2.0) ; (python_version < "3.3") and extra == 'testing'
Requires-Dist: typing-extensions (~=3.7.4) ; (python_version < "3.7") and extra == 'testing'
Requires-Dist: types-six (~=0.1.7) ; (python_version > "3.4") and extra == 'testing'
Requires-Dist: types-setuptools (~=57.0.0) ; (python_version > "3.4") and extra == 'testing'
Requires-Dist: types-mock (~=0.1.3) ; (python_version > "3.4") and extra == 'testing'
Requires-Dist: types-requests (~=2.25.6) ; (python_version > "3.4") and extra == 'testing'
Requires-Dist: pytest-asyncio (~=0.10.0) ; (python_version > "3.4") and extra == 'testing'
Requires-Dist: Faker (~=5.0.0) ; (python_version > "3.4") and extra == 'testing'
Requires-Dist: mypy (<=0.910,~=0.740) ; (python_version > "3.4" and python_version < "3.7") and extra == 'testing'
Requires-Dist: types-pytz ; (python_version > "3.6") and extra == 'testing'
Requires-Dist: types-redis ; (python_version > "3.6") and extra == 'testing'
Requires-Dist: mypy (~=0.991) ; (python_version >= "3.7") and extra == 'testing'
Requires-Dist: typing-extensions (~=3.10) ; (python_version >= "3.7") and extra == 'testing'
